README.md
setup.cfg
setup.py
Microlancer/__init__.py
Microlancer.egg-info/PKG-INFO
Microlancer.egg-info/SOURCES.txt
Microlancer.egg-info/dependency_links.txt
Microlancer.egg-info/requires.txt
Microlancer.egg-info/top_level.txt