Metadata-Version: 1.0
Name: Microlancer
Version: 1.2
Summary: Microlancer SDK
Home-page: https://github.com/Zenitsudeck/Microlancer
Author: Zenitsudeck
Author-email: UNKNOWN
License: UNKNOWN
Platform: UNKNOWN
